sensitive_data_gaurd/__init__.py
sensitive_data_gaurd/config.py
sensitive_data_gaurd/detect_info.py
sensitive_data_gaurd/test_detect.py
src/__init__.py
src/config.py
src/detect_info.py
testing/__init__.py
testing/test_detect.py
sensitive_data_guard-0.0.5.dist-info/LICENSE
sensitive_data_guard-0.0.5.dist-info/METADATA
sensitive_data_guard-0.0.5.dist-info/WHEEL
sensitive_data_guard-0.0.5.dist-info/top_level.txt
sensitive_data_guard-0.0.5.dist-info/RECORD
