Metadata-Version: 2.1
Name: sensitive-data-guard
Version: 0.0.5
Summary: utility package designed to detect sensitive 
Author: Lavanya
Author-email: lavanya.narang@dataverze.ai
Classifier: Programming Language :: Python :: 3
Classifier: License :: OSI Approved :: MIT License
Classifier: Operating System :: OS Independent
Requires-Python: >=3.7
License-File: LICENSE
